Metadata-Version: 2.1
Name: Jevents
Version: 1.1.3
Summary: Simple to use Utilities package for creating EventEmitters and implementing data observers.
Home-page: https://github.com/Jaimeloeuf/Jevents
Author: Jaime Loeuf
Author-email: jaimeloeuf@gmail.com
License: MIT
Keywords: data_observer EventEmitters events observers watch
Platform: UNKNOWN
Classifier: Development Status :: 4 - Beta
Classifier: Intended Audience :: Developers
Classifier: Environment :: Console
Classifier: License :: OSI Approved :: MIT License
Classifier: Natural Language :: English
Classifier: Programming Language :: Python :: 3.7
Classifier: Topic :: Utilities
